antarpy_dao/AntarpyLogging.py
antarpy_dao/AntarpyNeo4jBookmarkManager.py
antarpy_dao/AntarpyNeo4jDatasource.py
antarpy_dao/AntarpyNeo4jRetryPolicy.py
antarpy_dao/AntarpyNeo4jSession.py
antarpy_dao/__init__.py
antarpy_dao-1.1.dist-info/licenses/LICENSE
antarpy_dao-1.1.dist-info/METADATA
antarpy_dao-1.1.dist-info/WHEEL
antarpy_dao-1.1.dist-info/top_level.txt
antarpy_dao-1.1.dist-info/RECORD
