Metadata-Version: 2.4
Name: antarpy-dao
Version: 1.1
Summary: A Pythonic Neo4j DAO wrapper: clean sessions, retries, batch (CICT/APOC), bookmarks, transformers.
Author-email: Jeremy Chilvers <antarpydao@gmail.com>
License:                                  Apache License
Project-URL: Homepage, https://github.com/JeremyChilvers/antarpy_dao
Project-URL: Issues, https://github.com/JeremyChilvers/antarpy_dao/issues
Keywords: neo4j,graph,dao,database,rag,apoc,cict
Classifier: License :: OSI Approved :: Apache Software License
Classifier: Programming Language :: Python :: 3
Classifier: Programming Language :: Python :: 3 :: Only
Classifier: Topic :: Database
Requires-Python: >=3.9
License-File: LICENSE
Requires-Dist: neo4j>=5.15
Provides-Extra: dataframe
Requires-Dist: pandas>=1.5; extra == "dataframe"
Dynamic: license-file
